README.md
setup.py
stk_cage/__init__.py
stk_cage/cage.py
stk_cage.egg-info/PKG-INFO
stk_cage.egg-info/SOURCES.txt
stk_cage.egg-info/dependency_links.txt
stk_cage.egg-info/top_level.txt