Metadata-Version: 1.2
Name: stk-cage
Version: 0.0.3
Summary: build cage with STK
Home-page: UNKNOWN
Author: Kexin Zhang
Author-email: secret@secret.com
License: UNKNOWN
Platform: UNKNOWN
Classifier: Programming Language :: Python :: 3
Classifier: License :: OSI Approved :: MIT License
Classifier: Operating System :: OS Independent
Requires-Python: >=3.6
